ev3devrpyc.py
ev3devrpyc-1.0.1.dist-info/METADATA
ev3devrpyc-1.0.1.dist-info/WHEEL
ev3devrpyc-1.0.1.dist-info/top_level.txt
ev3devrpyc-1.0.1.dist-info/RECORD
